subwaylinegraph/Seoul.py
subwaylinegraph/__init__.py
subwaylinegraph/dataloader.py
subwaylinegraph/utils.py
test/__init__.py
test/test_dataloader.py
test/test_find_path.py
test/test_floyd.py
test/test_graph.py
test/test_line.py
test/test_sslg.py
test/test_transfer.py
subwaylinegraph-0.0.1.dist-info/METADATA
subwaylinegraph-0.0.1.dist-info/WHEEL
subwaylinegraph-0.0.1.dist-info/top_level.txt
subwaylinegraph-0.0.1.dist-info/RECORD
